{
  "rifampicin_resistance": {
    "n_studies": 152,
    "pooled_prevalence": 11.5,
    "ci_lower": 8.9,
    "ci_upper": 14.1,
    "i_squared": 87.3,
    "total_samples": 28560
  },
  "multidrug_resistant_tb": {
    "n_studies": 98,
    "pooled_prevalence": 4.8,
    "ci_lower": 3.7,
    "ci_upper": 5.9,
    "i_squared": 91.7,
    "total_samples": 18650
  },
  "extensively_drug_resistant": {
    "n_studies": 35,
    "pooled_prevalence": 0.4,
    "ci_lower": 0.2,
    "ci_upper": 0.6,
    "i_squared": 65.4,
    "total_samples": 8940
  },
  "isoniazid_resistance": {
    "n_studies": 42,
    "pooled_prevalence": 9.2,
    "ci_lower": 6.8,
    "ci_upper": 11.6,
    "i_squared": 79.8,
    "total_samples": 12340
  }
}